quboassistfunc-0.0.18.dist-info/METADATA
quboassistfunc-0.0.18.dist-info/WHEEL
quboassistfunc/__init__.py
quboassistfunc/quboassistfunc.cpython-39-darwin.so
quboassistfunc-0.0.18.dist-info/RECORD
